{
  "digest": "4f1e5bea269712a3da668057171e804fc70722b0681e018960c65764fb6a65ad",
  "snapshot": {
    "warp": "W0B",
    "global_step": 8050,
    "cycle": 0,
    "local": {
      "V": {
        "x": [],
        "x_try": [],
        "score": [],
        "score_try": []
      },
      "S": {
        "minscore": 999999.0,
        "seed": 0.0
      },
      "MEM": {}
    },
    "nodes": {
      "W0B:init": {
        "status": "DONE"
      },
      "W0B:step": {
        "status": "PENDING"
      },
      "W0B:score": {
        "status": "PENDING"
      }
    },
    "_ts": 1771599851.4514592
  }
}