{
  "digest": "7cb3544df1ffc1febe499b8697896728b3a9ee53b7ac34be7377d8614a7232b4",
  "snapshot": {
    "warp": "W1",
    "global_step": 8106,
    "cycle": 0,
    "local": {
      "V": {
        "x": [
          6.0,
          6.0,
          6.0,
          6.0
        ],
        "x_try": [
          6.0,
          6.0,
          6.0,
          6.0
        ],
        "score": [
          999999.0,
          999999.0,
          999999.0,
          999999.0
        ],
        "score_try": [
          999999.0,
          999999.0,
          999999.0,
          999999.0
        ]
      },
      "S": {
        "minscore": 999999.0,
        "seed": 0.0
      },
      "MEM": {}
    },
    "nodes": {
      "W1:init": {
        "status": "DONE"
      },
      "W1:step": {
        "status": "PENDING"
      },
      "W1:score": {
        "status": "PENDING"
      }
    },
    "_ts": 1771599852.5370524
  }
}