{
  "digest": "dc390bb60a073c9620d7ad38542fdc196577352653a2d81e4a73752563d893ca",
  "snapshot": {
    "warp": "W0",
    "global_step": 8764,
    "cycle": 0,
    "local": {
      "V": {
        "x": [
          6.0,
          6.0,
          6.0,
          6.0
        ],
        "x_try": [
          6.0,
          6.0,
          6.0,
          6.0
        ],
        "score": [
          999999.0,
          999999.0,
          999999.0,
          999999.0
        ],
        "score_try": [
          999999.0,
          999999.0,
          999999.0,
          999999.0
        ]
      },
      "S": {
        "minscore": 999999.0,
        "seed": 0.0
      },
      "MEM": {}
    },
    "nodes": {
      "W0:init": {
        "status": "DONE"
      },
      "W0:step": {
        "status": "PENDING"
      },
      "W0:score": {
        "status": "PENDING"
      }
    },
    "_ts": 1771599865.5295546
  }
}